MANIFEST.in
README.rst
bootstrap-buildout.py
buildout.cfg
requirements.txt
setup.py
version.txt
bob/__init__.py
bob.db.cuhk_cufsf.egg-info/PKG-INFO
bob.db.cuhk_cufsf.egg-info/SOURCES.txt
bob.db.cuhk_cufsf.egg-info/dependency_links.txt
bob.db.cuhk_cufsf.egg-info/entry_points.txt
bob.db.cuhk_cufsf.egg-info/namespace_packages.txt
bob.db.cuhk_cufsf.egg-info/not-zip-safe
bob.db.cuhk_cufsf.egg-info/requires.txt
bob.db.cuhk_cufsf.egg-info/top_level.txt
bob/db/__init__.py
bob/db/cuhk_cufsf/__init__.py
bob/db/cuhk_cufsf/create.py
bob/db/cuhk_cufsf/driver.py
bob/db/cuhk_cufsf/models.py
bob/db/cuhk_cufsf/query.py
bob/db/cuhk_cufsf/test.py
bob/db/cuhk_cufsf/utils.py
doc/conf.py
doc/guide.rst
doc/index.rst
doc/py_api.rst